.gitignore
MANIFEST.in
README.rst
setup.py
adi/__init__.py
adi.devgen.egg-info/PKG-INFO
adi.devgen.egg-info/SOURCES.txt
adi.devgen.egg-info/dependency_links.txt
adi.devgen.egg-info/entry_points.txt
adi.devgen.egg-info/namespace_packages.txt
adi.devgen.egg-info/not-zip-safe
adi.devgen.egg-info/requires.txt
adi.devgen.egg-info/top_level.txt
adi/devgen/__init__.py
adi/devgen/devgen.py
adi/devgen/helpers/README.txt
adi/devgen/helpers/__init__.py
adi/devgen/helpers/collections.py
adi/devgen/helpers/content.py
adi/devgen/helpers/debug.py
adi/devgen/helpers/events.py
adi/devgen/helpers/misc.py
adi/devgen/helpers/permissions.py
adi/devgen/helpers/times.py
adi/devgen/helpers/users.py
adi/devgen/helpers/versioning.py
adi/devgen/helpers/workflow.py
adi/devgen/scripts/README.txt
adi/devgen/scripts/__init__.py
adi/devgen/scripts/conventions.py
adi/devgen/scripts/create.py
adi/devgen/scripts/git.py
adi/devgen/scripts/install.py
adi/devgen/scripts/skels.py
docs/CHANGES.rst
docs/INSTALL.txt
docs/LICENSE.GPL
docs/LICENSE.txt