Metadata-Version: 1.1
Name: adi.devgen
Version: 1.3
Summary: Misc helper-scripts for creating and expanding Plone-Add-Ons.
Home-page: https://github.com/ida/adi.devgen
Author: Ida Ebkes
Author-email: contact@ida-ebkes.eu
License: GPL
Platform: UNKNOWN
Classifier: Framework :: Plone
Classifier: Programming Language :: Python
